tonclient/__init__.py
tonclient/abi.py
tonclient/boc.py
tonclient/client.py
tonclient/crypto.py
tonclient/debot.py
tonclient/errors.py
tonclient/module.py
tonclient/net.py
tonclient/objects.py
tonclient/processing.py
tonclient/proofs.py
tonclient/tvm.py
tonclient/types.py
tonclient/utils.py
tonclient/bin/ton-rust-client.arm64.dylib
tonclient/bin/ton-rust-client.dll
tonclient/bin/ton-rust-client.dylib
tonclient/bin/ton-rust-client.so
tonclient/bindings/__init__.py
tonclient/bindings/lib.py
tonclient/bindings/types.py
tonclient/test/__init__.py
tonclient/test/helpers.py
tonclient/test/test_abi.py
tonclient/test/test_async.py
tonclient/test/test_boc.py
tonclient/test/test_client.py
tonclient/test/test_crypto.py
tonclient/test/test_net.py
tonclient/test/test_processing.py
tonclient/test/test_tvm.py
tonclient/test/test_utils.py
tonclient/test/samples/Debot.abi.json
tonclient/test/samples/Debot.tvc
tonclient/test/samples/Debot2.abi.json
tonclient/test/samples/Debot2.tvc
tonclient/test/samples/Debot3.abi.json
tonclient/test/samples/Debot3.tvc
tonclient/test/samples/Debot4.abi.json
tonclient/test/samples/Debot4.tvc
tonclient/test/samples/Debot5.abi.json
tonclient/test/samples/Debot5.tvc
tonclient/test/samples/Debot7.abi.json
tonclient/test/samples/Debot7.tvc
tonclient/test/samples/DebotPairA.abi.json
tonclient/test/samples/DebotPairA.tvc
tonclient/test/samples/DebotPairB.abi.json
tonclient/test/samples/DebotPairB.tvc
tonclient/test/samples/DebotTarget.abi.json
tonclient/test/samples/DebotTarget.tvc
tonclient/test/samples/Events.abi.json
tonclient/test/samples/Events.tvc
tonclient/test/samples/Giver-v2.abi.json
tonclient/test/samples/Giver.abi.json
tonclient/test/samples/Hello.abi.json
tonclient/test/samples/Hello.tvc
tonclient/test/samples/PriceXchg.abi.json
tonclient/test/samples/Subscription.abi.json
tonclient/test/samples/Subscription.tvc
tonclient/test/samples/aes.iv.bin
tonclient/test/samples/aes.plaintext.bin
tonclient/test/samples/aes.plaintext.for.padding.bin
ton_client_py-1.44.1.0.dist-info/LICENSE
ton_client_py-1.44.1.0.dist-info/METADATA
ton_client_py-1.44.1.0.dist-info/WHEEL
ton_client_py-1.44.1.0.dist-info/top_level.txt
ton_client_py-1.44.1.0.dist-info/RECORD
