Metadata-Version: 2.1
Name: ton-client-py
Version: 1.44.1.0
Summary: Python SDK for Everscale
Home-page: https://github.com/move-ton/ton-client-py
Author: MoveTON
Author-email: 
Classifier: Programming Language :: Python :: 3
Classifier: License :: OSI Approved :: Apache Software License
Classifier: Operating System :: OS Independent
Requires-Python: >=3.7
License-File: LICENSE
